saracenpypacks/__init__.py
saracenpypacks-1.2.dist-info/METADATA
saracenpypacks-1.2.dist-info/WHEEL
saracenpypacks-1.2.dist-info/top_level.txt
saracenpypacks-1.2.dist-info/RECORD
